megrim/Cas9DevelopmentScript.py
megrim/__init__.py
megrim/accessory_functions.py
megrim/basic_qc.py
megrim/environment.py
megrim/extract_file_system_content.py
megrim/genome_geometry.py
megrim/infographic_plots.py
megrim/project_manager.py
megrim/project_registry.py
megrim/project_selector.py
megrim/reference_data_registry.py
megrim/reference_genome.py
megrim/reproducible_research.py
megrim/scan_content.py
megrim/data/FontAwesome5Free-Solid-900.otf
megrim/data/ONT_logo.png
megrim-0.3.1.dist-info/LICENSE
megrim-0.3.1.dist-info/METADATA
megrim-0.3.1.dist-info/WHEEL
megrim-0.3.1.dist-info/top_level.txt
megrim-0.3.1.dist-info/RECORD
